Workbook

Sheet Dados Brutos
A1: DADOS BRUTOS — Planejamento 2026 (fonte: Planejamento_2026_Cloud_Ago.xlsx)
A2: Valores digitados aqui em azul = extraidos da planilha original. Nao editar formulas (preto).
A4: Categoria | B4: Estimado/mes | C4: Jan | D4: Fev | E4: Mar | F4: Abr | G4: Mai | H4: Jun | I4: Jul | J4: Ago | K4: Total Jan-Ago | L4: % do Total
A5: Cuidados Pessoais | B5: 4539 | C5: 4399 | D5: 13271 | E5: 13714 | F5: 11670.78 | G5: 7811.65 | H5: 19448.56 | I5: 4789.33 | J5: 6429.09 | K5: =SUM(C5:J5) -> 81533.41 | L5: =K5/$K$17 -> 0.24847541
A6: Transporte | B6: 2358 | C6: 1639 | D6: 1672 | E6: 3926 | F6: 3979.92 | G6: 5650.86 | H6: 13043.42 | I6: 5875.32 | J6: 27237.21 | K6: =SUM(C6:J6) -> 63023.73 | L6: =K6/$K$17 -> 0.19206662
A7: Extras | B7: 300 | C7: 995 | D7: 1908 | E7: 820 | F7: 7399.96 | G7: 9185.33 | H7: 7021.01 | I7: 20887.18 | J7: 8443.48 | K7: =SUM(C7:J7) -> 56659.96 | L7: =K7/$K$17 -> 0.17267285
A8: Moradia | B8: 4476 | C8: 8056 | D8: 6016 | E8: 4951 | F8: 6273.56 | G8: 5175.95 | H8: 7602.44 | I8: 3700.75 | J8: 2658.59 | K8: =SUM(C8:J8) -> 44434.29 | L8: =K8/$K$17 -> 0.13541477
A9: Lazer | B9: 3600 | C9: 5269 | D9: 5889 | E9: 3721 | F9: 4721.71 | G9: 4608.4 | H9: 7985.84 | I9: 2633.79 | J9: 5329.26 | K9: =SUM(C9:J9) -> 40158 | L9: =K9/$K$17 -> 0.12238266
A10: Educacao | B10: 1880 | C10: 1828 | D10: 1862 | E10: 4420 | F10: 776.5 | G10: 3276.81 | H10: 1013.13 | I10: 1064.13 | J10: 2404.61 | K10: =SUM(C10:J10) -> 16645.18 | L10: =K10/$K$17 -> 0.050726663
A11: Impostos | B11: 812 | C11: 812 | D11: 815 | E11: 293 | F11: 128 | G11: 1204.92 | H11: 2152.15 | I11: 1204.92 | J11: 1239.59 | K11: =SUM(C11:J11) -> 7849.58 | L11: =K11/$K$17 -> 0.02392182
A12: Assinaturas | B12: 371 | C12: 336 | D12: 336 | E12: 2959 | F12: 567.17 | G12: 1148.77 | H12: 575.57 | I12: 650.56 | J12: 1211.1 | K12: =SUM(C12:J12) -> 7784.17 | L12: =K12/$K$17 -> 0.023722481
A13: Tarifas Financeiras | B13: 319 | C13: 319 | D13: 119 | E13: 322 | F13: 160.26 | G13: 224.12 | H13: 359.88 | I13: 1653.62 | J13: 1449.82 | K13: =SUM(C13:J13) -> 4607.7 | L13: =K13/$K$17 -> 0.014042098
A14: Servicos | B14: 460 | C14: 460 | D14: 65 | E14: 305 | F14: 1351.09 | G14: 0 | H14: 747.94 | I14: 0 | J14: 0 | K14: =SUM(C14:J14) -> 2929.03 | L14: =K14/$K$17 -> 0.0089263029
A15: Social | B15: 400 | C15: 0 | D15: 553 | E15: 400 | F15: 323.06 | G15: 87.75 | H15: 632.75 | I15: 87.75 | J15: 425.37 | K15: =SUM(C15:J15) -> 2509.68 | L15: =K15/$K$17 -> 0.0076483218
A17: TOTAL (soma das categorias) | B17: =SUM(B5:B15) -> 19515 | C17: =SUM(C5:C15) -> 24113 | D17: =SUM(D5:D15) -> 32506 | E17: =SUM(E5:E15) -> 35831 | F17: =SUM(F5:F15) -> 37352.01 | G17: =SUM(G5:G15) -> 38374.56 | H17: =SUM(H5:H15) -> 60582.69 | I17: =SUM(I5:I15) -> 42547.35 | ... K17: =SUM(K5:K15) -> 328134.73
A19: TOTAL OFICIAL (linha TOTAL da planilha original) | B19: 18436 | C19: 22339 | D19: 30414 | E19: 34384 | F19: 37352.01 | G19: 38374.56 | H19: 60582.69 | I19: 42547.35 | J19: 56828.12 | K19: =SUM(C19:J19) -> 322821.73
A20: Divergencia (Soma categorias - Total oficial) | C20: =C17-C19 -> 1774 | D20: =D17-D19 -> 2092 | E20: =E17-E19 -> 1447 | F20: =F17-F19 -> 0 | G20: =G17-G19 -> 0 | H20: =H17-H19 -> 0 | I20: =I17-I19 -> 0 | J20: =J17-J19 -> 0 | K20: =K17-K19 -> 5313
A22: Total em EUR (conversao fixa da planilha original) | C22: 3723.17 | D22: 5069 | E22: 5730.67 | F22: 6225.34 | G22: 6395.76 | H22: 10097.12 | I22: 7091.23 | J22: 9471.35
A23: Cambio implicito (BRL/EUR) | C23: =C19/C22 -> 5.9999946 | D23: =D19/D22 -> 6 | E23: =E19/E22 -> 5.9999965 | F23: =F19/F22 -> 5.9999952 | G23: =G19/G22 -> 6 | H23: =H19/H22 -> 5.999997 | I23: =I19/I22 -> 5.9999958 | J23: =J19/J22 -> 6.0000021
A25: Total gasto fora do planejado (ano, declarado na planilha original) | B25: 175333.73

Sheet Resumo Executivo
B2: RESUMO EXECUTIVO — Jan a Ago 2026
B3: Consolidado a partir de Planejamento_2026_Cloud_Ago.xlsx | Atualize a aba 'Dados Brutos' todo mes
B5: Total gasto (Jan-Ago) | D5: Media mensal | F5: Total orcado (estimado x8)
B6: ='Dados Brutos'!K19 -> 322821.73 | D6: ='Dados Brutos'!K19/8 -> 40352.716 | F6: ='Dados Brutos'!B19*8 -> 147488
B9: Estourado vs. orcado | D9: % acima do orcado | F9: Mes de maior gasto
B10: ='Dados Brutos'!K19-('Dados Brutos'!B19*8) -> 175333.73 | D10: =('Dados Brutos'!K19-('Dados Brutos'!B19*8))/('Dados Brutos'!B19*8) -> 1.1888 | F10: =INDEX('Dados Brutos'!C4:J4,MATCH(MAX('Dados Brutos'!C19:J19),'Dados Brutos'!C19:J19,0)) -> Jun
B13: Gasto total fora do planejado no ano (todas as categorias, declarado na planilha original): | F13: ='Dados Brutos'!B25 -> 175333.73
B16: Mes | C16: Gasto Real | D16: Orcado
B17: Jan | C17: ='Dados Brutos'!C19 -> 22339 | D17: ='Dados Brutos'!B19 -> 18436
B18: Fev | C18: ='Dados Brutos'!D19 -> 30414 | D18: ='Dados Brutos'!B19 -> 18436
B19: Mar | C19: ='Dados Brutos'!E19 -> 34384 | D19: ='Dados Brutos'!B19 -> 18436
B20: Abr | C20: ='Dados Brutos'!F19 -> 37352.01 | D20: ='Dados Brutos'!B19 -> 18436
B21: Mai | C21: ='Dados Brutos'!G19 -> 38374.56 | D21: ='Dados Brutos'!B19 -> 18436
B22: Jun | C22: ='Dados Brutos'!H19 -> 60582.69 | D22: ='Dados Brutos'!B19 -> 18436
B23: Jul | C23: ='Dados Brutos'!I19 -> 42547.35 | D23: ='Dados Brutos'!B19 -> 18436
B24: Ago | C24: ='Dados Brutos'!J19 -> 56828.12 | D24: ='Dados Brutos'!B19 -> 18436

Sheet Por Categoria
A1: GASTOS POR CATEGORIA — Jan a Ago 2026 (ordenado por total)
A3: Categoria | B3: Total Jan-Ago | C3: % do Total | D3: Media/mes | E3: Estimado/mes | F3: Var. vs Estimado (media)
A4: ='Dados Brutos'!A5 -> Cuidados Pessoais | B4: ='Dados Brutos'!K5 -> 81533.41 | C4: ='Dados Brutos'!K5/'Dados Brutos'!K$19 -> 0.25256481 | D4: ='Dados Brutos'!K5/8 -> 10191.676 | E4: ='Dados Brutos'!B5 -> 4539 | F4: =(D4-E4)/E4 -> 1.2453572
A5: ='Dados Brutos'!A6 -> Transporte | B5: ='Dados Brutos'!K6 -> 63023.73 | C5: ='Dados Brutos'!K6/'Dados Brutos'!K$19 -> 0.19522766 | D5: ='Dados Brutos'!K6/8 -> 7877.9663 | E5: ='Dados Brutos'!B6 -> 2358 | F5: =(D5-E5)/E5 -> 2.3409526
A6: ='Dados Brutos'!A7 -> Extras | B6: ='Dados Brutos'!K7 -> 56659.96 | C6: ='Dados Brutos'!K7/'Dados Brutos'!K$19 -> 0.1755147 | D6: ='Dados Brutos'!K7/8 -> 7082.495 | E6: ='Dados Brutos'!B7 -> 300 | F6: =(D6-E6)/E6 -> 22.608317
A7: ='Dados Brutos'!A8 -> Moradia | B7: ='Dados Brutos'!K8 -> 44434.29 | C7: ='Dados Brutos'!K8/'Dados Brutos'!K$19 -> 0.13764343 | D7: ='Dados Brutos'!K8/8 -> 5554.2863 | E7: ='Dados Brutos'!B8 -> 4476 | F7: =(D7-E7)/E7 -> 0.24090399
A8: ='Dados Brutos'!A9 -> Lazer | B8: ='Dados Brutos'!K9 -> 40158 | C8: ='Dados Brutos'!K9/'Dados Brutos'!K$19 -> 0.12439683 | D8: ='Dados Brutos'!K9/8 -> 5019.75 | E8: ='Dados Brutos'!B9 -> 3600 | F8: =(D8-E8)/E8 -> 0.394375
A9: ='Dados Brutos'!A10 -> Educacao | B9: ='Dados Brutos'!K10 -> 16645.18 | C9: ='Dados Brutos'!K10/'Dados Brutos'!K$19 -> 0.051561523 | D9: ='Dados Brutos'!K10/8 -> 2080.6475 | E9: ='Dados Brutos'!B10 -> 1880 | F9: =(D9-E9)/E9 -> 0.10672739
A10: ='Dados Brutos'!A11 -> Impostos | B10: ='Dados Brutos'!K11 -> 7849.58 | C10: ='Dados Brutos'!K11/'Dados Brutos'!K$19 -> 0.024315525 | D10: ='Dados Brutos'!K11/8 -> 981.1975 | E10: ='Dados Brutos'!B11 -> 812 | F10: =(D10-E10)/E10 -> 0.20837131
A11: ='Dados Brutos'!A12 -> Assinaturas | B11: ='Dados Brutos'!K12 -> 7784.17 | C11: ='Dados Brutos'!K12/'Dados Brutos'!K$19 -> 0.024112906 | D11: ='Dados Brutos'!K12/8 -> 973.02125 | E11: ='Dados Brutos'!B12 -> 371 | F11: =(D11-E11)/E11 -> 1.6226988
A12: ='Dados Brutos'!A13 -> Tarifas Financeiras | B12: ='Dados Brutos'!K13 -> 4607.7 | C12: ='Dados Brutos'!K13/'Dados Brutos'!K$19 -> 0.014273203 | D12: ='Dados Brutos'!K13/8 -> 575.9625 | E12: ='Dados Brutos'!B13 -> 319 | F12: =(D12-E12)/E12 -> 0.80552508
A13: ='Dados Brutos'!A14 -> Servicos | B13: ='Dados Brutos'!K14 -> 2929.03 | C13: ='Dados Brutos'!K14/'Dados Brutos'!K$19 -> 0.009073212 | D13: ='Dados Brutos'!K14/8 -> 366.12875 | E13: ='Dados Brutos'!B14 -> 460 | F13: =(D13-E13)/E13 -> -0.20406793
A14: ='Dados Brutos'!A15 -> Social | B14: ='Dados Brutos'!K15 -> 2509.68 | C14: ='Dados Brutos'!K15/'Dados Brutos'!K$19 -> 0.0077741979 | D14: ='Dados Brutos'!K15/8 -> 313.71 | E14: ='Dados Brutos'!B15 -> 400 | F14: =(D14-E14)/E14 -> -0.215725
A15: TOTAL | B15: =SUM(B4:B14) -> 328134.73 | C15: =SUM(C4:C14) -> 1.016458

Sheet Alertas e Insights
A1: ALERTAS, INCONSISTENCIAS E INSIGHTS
A3: BLIND SPOT CRITICO
A4: Esta planilha rastreia apenas SAIDAS. Nao ha nenhuma linha de RENDA/ENTRADA.
A5: Sem receita registrada, nao e possivel calcular taxa de poupanca real, comprometimento
A6: de renda (%) ou 'saude financeira' de fato -- apenas o volume e padrao de gasto.
A7: Recomendacao: adicionar uma aba/linha de Receita Mensal (BRL e EUR) antes do proximo ciclo.
A9: INCONSISTENCIA NUMERICA DETECTADA (Jan-Mar)
A10: A soma das categorias diverge do TOTAL declarado na planilha original em Jan, Fev e Mar
A11: (diferencas de R$1.774, R$2.092 e R$1.447 -- ver aba 'Dados Brutos', linha 'Divergencia').
A12: De Abr a Ago a soma bate exatamente com o total oficial (divergencia zero).
A13: Recomendacao: auditar formulas/celulas de Jan-Mar na planilha original -- provavel
A14: categoria ou lancamento fora do range somado pela formula de TOTAL desses 3 meses.
... A37: como piso realista, e negociar reducoes categoria a categoria a partir dai.
